{
  "initial_balance": 10000.0,
  "final_balance": 4036.489999999884,
  "net_profit": -5963.51000000012,
  "return_pct": -59.63510000000116,
  "total_trades": 201,
  "wins": 57,
  "losses": 144,
  "win_rate": 0.2835820895522388,
  "gross_profit": 7749.000000000044,
  "gross_loss": 13712.510000000164,
  "profit_factor": 0.5651044192492805,
  "max_drawdown_pct": 60.67864271457197,
  "max_active_pairs": 3,
  "pairs_with_signals": 42,
  "period_start_utc": "2025-12-12 01:45:13.800022+00:00",
  "period_end_utc": "2026-03-12 01:45:13.800022+00:00",
  "pairs_discovered": 52,
  "pairs_processed": 42,
  "pairs_skipped": 10,
  "lot_mode": "fixed_lot",
  "fixed_lot": 0.01,
  "backtest_fast_tf": "H1",
  "backtest_slow_tf": "H4"
}